{
    "scene1_baseline": {
        "Mental_Demand": 60,
        "Physical_Demand": 20,
        "Temporal_Demand": 40,
        "Perforamnce": 50,
        "Effort": 40,
        "Frustration": 30,
        "Overall": 47.34
    },
    "scene1_noise_cancellation": {
        "Mental_Demand": 70,
        "Physical_Demand": 50,
        "Temporal_Demand": 70,
        "Perforamnce": 60,
        "Effort": 60,
        "Frustration": 60,
        "Overall": 65.34
    },
    "scene1_proxies": {
        "Mental_Demand": 20,
        "Physical_Demand": 10,
        "Temporal_Demand": 10,
        "Perforamnce": 40,
        "Effort": 10,
        "Frustration": 10,
        "Overall": 19.34
    },
    "scene2_baseline": {
        "Mental_Demand": 50,
        "Physical_Demand": 40,
        "Temporal_Demand": 40,
        "Perforamnce": 50,
        "Effort": 40,
        "Frustration": 30,
        "Overall": 46
    },
    "scene2_noise_cancellation": {
        "Mental_Demand": 70,
        "Physical_Demand": 50,
        "Temporal_Demand": 50,
        "Perforamnce": 70,
        "Effort": 50,
        "Frustration": 60,
        "Overall": 62
    },
    "scene2_proxies": {
        "Mental_Demand": 50,
        "Physical_Demand": 30,
        "Temporal_Demand": 30,
        "Perforamnce": 60,
        "Effort": 30,
        "Frustration": 20,
        "Overall": 44.67
    },
    "scene3_baseline": {
        "Mental_Demand": 60,
        "Physical_Demand": 30,
        "Temporal_Demand": 60,
        "Perforamnce": 70,
        "Effort": 50,
        "Frustration": 60,
        "Overall": 61.34
    },
    "scene3_noise_cancellation": {
        "Mental_Demand": 50,
        "Physical_Demand": 5,
        "Temporal_Demand": 40,
        "Perforamnce": 50,
        "Effort": 60,
        "Frustration": 30,
        "Overall": 45
    },
    "scene3_proxies": {
        "Mental_Demand": 10,
        "Physical_Demand": 5,
        "Temporal_Demand": 30,
        "Perforamnce": 40,
        "Effort": 10,
        "Frustration": 10,
        "Overall": 18.34
    }
}