{
    "LocationLogs": [
        {
            "objectName": "whiteCane",
            "clipName": "whiteCane",
            "x": -231.25,
            "y": 64.89,
            "z": 17.75
        },
        {
            "objectName": "voiceAssistant",
            "clipName": "voiceAssistant",
            "x": -232.46,
            "y": 69.89,
            "z": 17.75
        },
        {
            "objectName": "voiceMessage",
            "clipName": "voiceMessage",
            "x": -230.0,
            "y": 69.89,
            "z": 17.75
        },
        {
            "objectName": "StreetSellerStand1",
            "clipName": "vendorNoise",
            "x": -276.6103,
            "y": 69.96448,
            "z": 21.2684574
        },
        {
            "objectName": "StreetSellerStand2",
            "clipName": "vendorNoise",
            "x": -292.355621,
            "y": 69.96448,
            "z": 2.94022465
        },
        {
            "objectName": "StreetSellerStand3",
            "clipName": "vendorNoise",
            "x": -268.741333,
            "y": 69.96448,
            "z": 0.639122
        },
        {
            "objectName": "StreetSellerStand4",
            "clipName": "vendorNoise",
            "x": -336.711,
            "y": 69.96448,
            "z": 2.96589851
        },
        {
            "objectName": "StreetSellerStand5",
            "clipName": "vendorNoise",
            "x": -353.691559,
            "y": 69.96448,
            "z": 2.97708035
        },
        {
            "objectName": "StreetSellerStand6",
            "clipName": "vendorNoise",
            "x": -318.5104,
            "y": 69.96448,
            "z": 21.4415112
        },
        {
            "objectName": "StreetSellerStand7",
            "clipName": "vendorNoise",
            "x": -340.6649,
            "y": 69.96448,
            "z": 21.8141556
        },
        {
            "objectName": "StreetSellerStand8",
            "clipName": "vendorNoise",
            "x": -290.666,
            "y": 69.96448,
            "z": 21.8136215
        },
        {
            "objectName": "StreetSellerStand9",
            "clipName": "vendorNoise",
            "x": -371.264557,
            "y": 69.96448,
            "z": 21.8142853
        },
        {
            "objectName": "StreetSellerStand10",
            "clipName": "vendorNoise",
            "x": -375.296051,
            "y": 69.96448,
            "z": 2.39709854
        },
        {
            "objectName": "carStraight1",
            "clipName": "carNoiseSound",
            "x": -219.3,
            "y": 69.7699356,
            "z": 12.0
        },
        {
            "objectName": "carStraight2",
            "clipName": "carNoiseSound",
            "x": -219.3,
            "y": 69.7699356,
            "z": 12.0
        },
        {
            "objectName": "carStraight3",
            "clipName": "carNoiseSound",
            "x": -219.3,
            "y": 69.7699356,
            "z": 12.0
        },
        {
            "objectName": "carStraight4",
            "clipName": "carNoiseSound",
            "x": -219.3,
            "y": 69.7699356,
            "z": 12.0
        },
        {
            "objectName": "carTurn1",
            "clipName": "carNoiseSound",
            "x": -388.0,
            "y": 69.76,
            "z": 8.0
        },
        {
            "objectName": "carTurn2",
            "clipName": "carNoiseSound",
            "x": -388.0,
            "y": 69.76,
            "z": 8.0
        },
        {
            "objectName": "carTurn3",
            "clipName": "carNoiseSound",
            "x": -388.0,
            "y": 69.76,
            "z": 8.0
        },
        {
            "objectName": "carTurn4",
            "clipName": "carNoiseSound",
            "x": -388.0,
            "y": 69.76,
            "z": 8.0
        },
        {
            "objectName": "CrowdController1",
            "clipName": "crowdNoise3",
            "x": -245.351013,
            "y": 70.48651,
            "z": 21.49
        },
        {
            "objectName": "CrowdController2",
            "clipName": "crowdNoise3",
            "x": -260.6,
            "y": 70.48651,
            "z": 21.49
        },
        {
            "objectName": "CrowdController3",
            "clipName": "crowdNoise3",
            "x": -279.4,
            "y": 70.48651,
            "z": 1.30000019
        },
        {
            "objectName": "CrowdController4",
            "clipName": "crowdNoise3",
            "x": -304.751,
            "y": 70.48651,
            "z": 21.49
        },
        {
            "objectName": "CrowdController5",
            "clipName": "crowdNoise3",
            "x": -252.9,
            "y": 70.48651,
            "z": 1.30000019
        },
        {
            "objectName": "CrowdController6",
            "clipName": "crowdNoise3",
            "x": -342.451019,
            "y": 70.48651,
            "z": 21.49
        },
        {
            "objectName": "CrowdController7",
            "clipName": "crowdNoise3",
            "x": -317.651,
            "y": 70.48651,
            "z": 1.30000019
        },
        {
            "objectName": "CrowdController8",
            "clipName": "crowdNoise3",
            "x": -333.8,
            "y": 70.48651,
            "z": 1.30000019
        },
        {
            "objectName": "CrowdController9",
            "clipName": "crowdNoise3",
            "x": -363.7,
            "y": 70.48651,
            "z": 1.30000019
        },
        {
            "objectName": "CrowdController10",
            "clipName": "crowdNoise3",
            "x": -383.9,
            "y": 70.48651,
            "z": 1.30000019
        },
        {
            "objectName": "constructionNoise1",
            "clipName": "constructionNoise",
            "x": -260.841156,
            "y": 70.19499,
            "z": 15.4999943
        },
        {
            "objectName": "constructionNoise2",
            "clipName": "constructionNoise",
            "x": -295.195129,
            "y": 70.19499,
            "z": 15.4999943
        },
        {
            "objectName": "constructionNoise3",
            "clipName": "constructionNoise",
            "x": -323.74353,
            "y": 70.19499,
            "z": 15.4999943
        },
        {
            "objectName": "constructionNoise4",
            "clipName": "constructionNoise",
            "x": -345.445862,
            "y": 70.19499,
            "z": 15.4999943
        },
        {
            "objectName": "constructionNoise5",
            "clipName": "constructionNoise",
            "x": -381.61438,
            "y": 70.19499,
            "z": 15.4999943
        }
    ],
    "EventLogs": [
        {
            "objectName": "voiceAssistant",
            "clipName": "voiceAssistant",
            "audioIsLoop": false,
            "distanceToPlayer": 2.46000671,
            "happenPlayerPos": -250.389114,
            "happenTime": 8.123535,
            "clipTime": 0.0,
            "volume": 0.5,
            "x": -252.849121,
            "y": 69.89,
            "z": 17.75,
            "enterOrExit": "enter"
        },
        {
            "objectName": "constructionNoise1",
            "clipName": "constructionNoise",
            "audioIsLoop": false,
            "distanceToPlayer": 8.831437,
            "happenPlayerPos": -252.3066,
            "happenTime": 8.890625,
            "clipTime": 0.0,
            "volume": 0.125,
            "x": -260.841156,
            "y": 70.19499,
            "z": 15.4999943,
            "enterOrExit": "enter"
        },
        {
            "objectName": "voiceAssistant",
            "clipName": "voiceAssistant",
            "audioIsLoop": false,
            "distanceToPlayer": 2.46000671,
            "happenPlayerPos": -255.724747,
            "happenTime": 10.2578125,
            "clipTime": 2.112,
            "volume": 0.5,
            "x": -258.184753,
            "y": 69.89,
            "z": 17.75,
            "enterOrExit": "exit"
        },
        {
            "objectName": "whiteCane",
            "clipName": "whiteCaneStone",
            "audioIsLoop": false,
            "distanceToPlayer": 5.153882,
            "happenPlayerPos": -263.894928,
            "happenTime": 13.5258789,
            "clipTime": 0.0,
            "volume": 0.125,
            "x": -265.144928,
            "y": 64.89,
            "z": 17.75,
            "enterOrExit": "enter"
        },
        {
            "objectName": "voiceMessage",
            "clipName": "voiceMessage",
            "audioIsLoop": false,
            "distanceToPlayer": 0.0,
            "happenPlayerPos": -264.478455,
            "happenTime": 13.7592773,
            "clipTime": 0.0,
            "volume": 0.5,
            "x": -264.478455,
            "y": 69.89,
            "z": 17.75,
            "enterOrExit": "enter"
        },
        {
            "objectName": "voiceMessage",
            "clipName": "voiceMessage",
            "audioIsLoop": false,
            "distanceToPlayer": 0.0,
            "happenPlayerPos": -268.896973,
            "happenTime": 15.5268555,
            "clipTime": 0.0,
            "volume": 0.5,
            "x": -268.896973,
            "y": 69.89,
            "z": 17.75,
            "enterOrExit": "exit"
        },
        {
            "objectName": "constructionNoise1",
            "clipName": "constructionNoise",
            "audioIsLoop": false,
            "distanceToPlayer": 8.932855,
            "happenPlayerPos": -269.480621,
            "happenTime": 15.7602539,
            "clipTime": 6.869167,
            "volume": 0.125,
            "x": -260.841156,
            "y": 70.19499,
            "z": 15.4999943,
            "enterOrExit": "exit"
        },
        {
            "objectName": "whiteCane",
            "clipName": "whiteCaneStone",
            "audioIsLoop": false,
            "distanceToPlayer": 5.153882,
            "happenPlayerPos": -269.9808,
            "happenTime": 15.9604492,
            "clipTime": 1.19466662,
            "volume": 0.125,
            "x": -271.2308,
            "y": 64.89,
            "z": 17.75,
            "enterOrExit": "exit"
        },
        {
            "objectName": "constructionNoise2",
            "clipName": "constructionNoise",
            "audioIsLoop": false,
            "distanceToPlayer": 9.402335,
            "happenPlayerPos": -286.071075,
            "happenTime": 22.3964844,
            "clipTime": 0.0,
            "volume": 0.125,
            "x": -295.195129,
            "y": 70.19499,
            "z": 15.4999943,
            "enterOrExit": "enter"
        },
        {
            "objectName": "voiceMessage",
            "clipName": "voiceMessage",
            "audioIsLoop": false,
            "distanceToPlayer": 0.0,
            "happenPlayerPos": -289.739166,
            "happenTime": 23.86377,
            "clipTime": 0.0,
            "volume": 0.5,
            "x": -289.739166,
            "y": 69.89,
            "z": 17.75,
            "enterOrExit": "enter"
        },
        {
            "objectName": "voiceAssistant",
            "clipName": "voiceAssistant",
            "audioIsLoop": false,
            "distanceToPlayer": 2.45999146,
            "happenPlayerPos": -291.9903,
            "happenTime": 24.76416,
            "clipTime": 0.0,
            "volume": 0.5,
            "x": -294.4503,
            "y": 69.89,
            "z": 17.75,
            "enterOrExit": "enter"
        },
        {
            "objectName": "voiceMessage",
            "clipName": "voiceMessage",
            "audioIsLoop": false,
            "distanceToPlayer": 0.0,
            "happenPlayerPos": -294.1579,
            "happenTime": 25.63086,
            "clipTime": 0.0,
            "volume": 0.5,
            "x": -294.1579,
            "y": 69.89,
            "z": 17.75,
            "enterOrExit": "exit"
        },
        {
            "objectName": "whiteCane",
            "clipName": "whiteCaneStone",
            "audioIsLoop": false,
            "distanceToPlayer": 5.153882,
            "happenPlayerPos": -294.824951,
            "happenTime": 25.89795,
            "clipTime": 0.0,
            "volume": 0.125,
            "x": -296.074951,
            "y": 64.89,
            "z": 17.75,
            "enterOrExit": "enter"
        },
        {
            "objectName": "voiceAssistant",
            "clipName": "voiceAssistant",
            "audioIsLoop": false,
            "distanceToPlayer": 2.45999146,
            "happenPlayerPos": -297.3258,
            "happenTime": 26.8984375,
            "clipTime": 2.112,
            "volume": 0.5,
            "x": -299.7858,
            "y": 69.89,
            "z": 17.75,
            "enterOrExit": "exit"
        },
        {
            "objectName": "whiteCane",
            "clipName": "whiteCaneStone",
            "audioIsLoop": false,
            "distanceToPlayer": 5.153882,
            "happenPlayerPos": -300.910828,
            "happenTime": 28.3320313,
            "clipTime": 1.152,
            "volume": 0.125,
            "x": -302.160828,
            "y": 64.89,
            "z": 17.75,
            "enterOrExit": "exit"
        },
        {
            "objectName": "constructionNoise2",
            "clipName": "constructionNoise",
            "audioIsLoop": false,
            "distanceToPlayer": 8.36408,
            "happenPlayerPos": -303.245117,
            "happenTime": 29.2661133,
            "clipTime": 6.86933327,
            "volume": 0.125,
            "x": -295.195129,
            "y": 70.19499,
            "z": 15.4999943,
            "enterOrExit": "exit"
        },
        {
            "objectName": "whiteCane",
            "clipName": "whiteCaneStone",
            "audioIsLoop": false,
            "distanceToPlayer": 5.153882,
            "happenPlayerPos": -307.246826,
            "happenTime": 30.8667,
            "clipTime": 0.0,
            "volume": 0.125,
            "x": -308.496826,
            "y": 64.89,
            "z": 17.75,
            "enterOrExit": "enter"
        },
        {
            "objectName": "whiteCane",
            "clipName": "whiteCaneStone",
            "audioIsLoop": false,
            "distanceToPlayer": 5.153882,
            "happenPlayerPos": -313.332642,
            "happenTime": 33.30127,
            "clipTime": 1.19466662,
            "volume": 0.125,
            "x": -314.582642,
            "y": 64.89,
            "z": 17.75,
            "enterOrExit": "exit"
        },
        {
            "objectName": "constructionNoise3",
            "clipName": "constructionNoise",
            "audioIsLoop": false,
            "distanceToPlayer": 9.923682,
            "happenPlayerPos": -314.0831,
            "happenTime": 33.6010742,
            "clipTime": 0.0,
            "volume": 0.125,
            "x": -323.74353,
            "y": 70.19499,
            "z": 15.4999943,
            "enterOrExit": "enter"
        },
        {
            "objectName": "voiceMessage",
            "clipName": "voiceMessage",
            "audioIsLoop": false,
            "distanceToPlayer": 0.0,
            "happenPlayerPos": -315.3337,
            "happenTime": 34.1015625,
            "clipTime": 0.0,
            "volume": 0.5,
            "x": -315.3337,
            "y": 69.89,
            "z": 17.75,
            "enterOrExit": "enter"
        },
        {
            "objectName": "voiceMessage",
            "clipName": "voiceMessage",
            "audioIsLoop": false,
            "distanceToPlayer": 0.0,
            "happenPlayerPos": -319.752045,
            "happenTime": 35.8686523,
            "clipTime": 0.0,
            "volume": 0.5,
            "x": -319.752045,
            "y": 69.89,
            "z": 17.75,
            "enterOrExit": "exit"
        },
        {
            "objectName": "voiceAssistant",
            "clipName": "voiceAssistant",
            "audioIsLoop": false,
            "distanceToPlayer": 2.45999146,
            "happenPlayerPos": -320.085663,
            "happenTime": 36.0019531,
            "clipTime": 0.0,
            "volume": 0.5,
            "x": -322.545654,
            "y": 69.89,
            "z": 17.75,
            "enterOrExit": "enter"
        },
        {
            "objectName": "voiceAssistant",
            "clipName": "voiceAssistant",
            "audioIsLoop": false,
            "distanceToPlayer": 2.45999146,
            "happenPlayerPos": -325.4214,
            "happenTime": 38.13623,
            "clipTime": 2.112,
            "volume": 0.5,
            "x": -327.881378,
            "y": 69.89,
            "z": 17.75,
            "enterOrExit": "exit"
        },
        {
            "objectName": "voiceAssistant",
            "clipName": "voiceAssistant",
            "audioIsLoop": false,
            "distanceToPlayer": 2.45999146,
            "happenPlayerPos": -328.756256,
            "happenTime": 39.4702148,
            "clipTime": 0.0,
            "volume": 0.5,
            "x": -331.216248,
            "y": 69.89,
            "z": 17.75,
            "enterOrExit": "enter"
        },
        {
            "objectName": "constructionNoise3",
            "clipName": "constructionNoise",
            "audioIsLoop": false,
            "distanceToPlayer": 7.849168,
            "happenPlayerPos": -331.2571,
            "happenTime": 40.4707031,
            "clipTime": 6.86933327,
            "volume": 0.125,
            "x": -323.74353,
            "y": 70.19499,
            "z": 15.4999943,
            "enterOrExit": "exit"
        },
        {
            "objectName": "voiceAssistant",
            "clipName": "voiceAssistant",
            "audioIsLoop": false,
            "distanceToPlayer": 2.45999146,
            "happenPlayerPos": -334.091827,
            "happenTime": 41.6044922,
            "clipTime": 2.112,
            "volume": 0.5,
            "x": -336.551819,
            "y": 69.89,
            "z": 17.75,
            "enterOrExit": "exit"
        },
        {
            "objectName": "constructionNoise4",
            "clipName": "constructionNoise",
            "audioIsLoop": false,
            "distanceToPlayer": 10.27418,
            "happenPlayerPos": -335.42572,
            "happenTime": 42.1381836,
            "clipTime": 0.0,
            "volume": 0.125,
            "x": -345.445862,
            "y": 70.19499,
            "z": 15.4999943,
            "enterOrExit": "enter"
        },
        {
            "objectName": "whiteCane",
            "clipName": "whiteCaneStone",
            "audioIsLoop": false,
            "distanceToPlayer": 5.153882,
            "happenPlayerPos": -344.335846,
            "happenTime": 45.70215,
            "clipTime": 0.0,
            "volume": 0.125,
            "x": -345.585846,
            "y": 64.89,
            "z": 17.75,
            "enterOrExit": "enter"
        },
        {
            "objectName": "voiceMessage",
            "clipName": "voiceMessage",
            "audioIsLoop": false,
            "distanceToPlayer": 0.0,
            "happenPlayerPos": -349.5883,
            "happenTime": 47.8032227,
            "clipTime": 0.0,
            "volume": 0.5,
            "x": -349.5883,
            "y": 69.89,
            "z": 17.75,
            "enterOrExit": "enter"
        },
        {
            "objectName": "whiteCane",
            "clipName": "whiteCaneStone",
            "audioIsLoop": false,
            "distanceToPlayer": 5.153882,
            "happenPlayerPos": -350.421967,
            "happenTime": 48.13672,
            "clipTime": 1.19466662,
            "volume": 0.125,
            "x": -351.671967,
            "y": 64.89,
            "z": 17.75,
            "enterOrExit": "exit"
        },
        {
            "objectName": "constructionNoise4",
            "clipName": "constructionNoise",
            "audioIsLoop": false,
            "distanceToPlayer": 7.57542944,
            "happenPlayerPos": -352.673,
            "happenTime": 49.03711,
            "clipTime": 0.0,
            "volume": 0.125,
            "x": -345.445862,
            "y": 70.19499,
            "z": 15.4999943,
            "enterOrExit": "exit"
        },
        {
            "objectName": "voiceMessage",
            "clipName": "voiceMessage",
            "audioIsLoop": false,
            "distanceToPlayer": 0.0,
            "happenPlayerPos": -354.007,
            "happenTime": 49.5708,
            "clipTime": 0.0,
            "volume": 0.5,
            "x": -354.007,
            "y": 69.89,
            "z": 17.75,
            "enterOrExit": "exit"
        },
        {
            "objectName": "whiteCane",
            "clipName": "whiteCaneStone",
            "audioIsLoop": false,
            "distanceToPlayer": 5.153882,
            "happenPlayerPos": -362.927582,
            "happenTime": 53.13867,
            "clipTime": 0.0,
            "volume": 0.125,
            "x": -364.177582,
            "y": 64.89,
            "z": 17.75,
            "enterOrExit": "enter"
        },
        {
            "objectName": "voiceAssistant",
            "clipName": "voiceAssistant",
            "audioIsLoop": false,
            "distanceToPlayer": 2.45999146,
            "happenPlayerPos": -365.261932,
            "happenTime": 54.0727539,
            "clipTime": 0.0,
            "volume": 0.5,
            "x": -367.721924,
            "y": 69.89,
            "z": 17.75,
            "enterOrExit": "enter"
        },
        {
            "objectName": "whiteCane",
            "clipName": "whiteCaneStone",
            "audioIsLoop": false,
            "distanceToPlayer": 5.153882,
            "happenPlayerPos": -369.013519,
            "happenTime": 55.5732422,
            "clipTime": 1.19466662,
            "volume": 0.125,
            "x": -370.263519,
            "y": 64.89,
            "z": 17.75,
            "enterOrExit": "exit"
        },
        {
            "objectName": "voiceAssistant",
            "clipName": "voiceAssistant",
            "audioIsLoop": false,
            "distanceToPlayer": 2.45999146,
            "happenPlayerPos": -370.6186,
            "happenTime": 56.215332,
            "clipTime": 2.112,
            "volume": 0.5,
            "x": -373.078583,
            "y": 69.89,
            "z": 17.75,
            "enterOrExit": "exit"
        },
        {
            "objectName": "constructionNoise5",
            "clipName": "constructionNoise",
            "audioIsLoop": false,
            "distanceToPlayer": 10.9016457,
            "happenPlayerPos": -370.9518,
            "happenTime": 56.3486328,
            "clipTime": 0.0,
            "volume": 0.125,
            "x": -381.61438,
            "y": 70.19499,
            "z": 15.4999943,
            "enterOrExit": "enter"
        },
        {
            "objectName": "voiceMessage",
            "clipName": "voiceMessage",
            "audioIsLoop": false,
            "distanceToPlayer": 0.0,
            "happenPlayerPos": -378.496582,
            "happenTime": 59.36621,
            "clipTime": 0.0,
            "volume": 0.5,
            "x": -378.496582,
            "y": 69.89,
            "z": 17.75,
            "enterOrExit": "enter"
        },
        {
            "objectName": "voiceMessage",
            "clipName": "voiceMessage",
            "audioIsLoop": false,
            "distanceToPlayer": 0.0,
            "happenPlayerPos": -382.915253,
            "happenTime": 61.13379,
            "clipTime": 0.0,
            "volume": 0.5,
            "x": -382.915253,
            "y": 69.89,
            "z": 17.75,
            "enterOrExit": "exit"
        },
        {
            "objectName": "constructionNoise5",
            "clipName": "constructionNoise",
            "audioIsLoop": false,
            "distanceToPlayer": 6.93534946,
            "happenPlayerPos": -388.1675,
            "happenTime": 63.2348633,
            "clipTime": 0.0,
            "volume": 0.125,
            "x": -381.61438,
            "y": 70.19499,
            "z": 15.4999943,
            "enterOrExit": "exit"
        }
    ],
    "TouchLogs": [
        {
            "touchTime": 9.224121,
            "touchPlayerPosition": -253.22374,
            "singleOrDouble": "2",
            "playingObjects": [
                "voiceAssistant",
                "constructionNoise"
            ]
        },
        {
            "touchTime": 11.925293,
            "touchPlayerPosition": -259.976624,
            "singleOrDouble": "3",
            "playingObjects": [
                "constructionNoise"
            ]
        },
        {
            "touchTime": 14.8930664,
            "touchPlayerPosition": -267.396362,
            "singleOrDouble": "4",
            "playingObjects": [
                "whiteCaneStone",
                "voiceMessage",
                "constructionNoise"
            ]
        },
        {
            "touchTime": 15.6601563,
            "touchPlayerPosition": -269.3137,
            "singleOrDouble": "1",
            "playingObjects": [
                "whiteCaneStone",
                "constructionNoise"
            ]
        },
        {
            "touchTime": 24.1303711,
            "touchPlayerPosition": -290.489563,
            "singleOrDouble": "3",
            "playingObjects": [
                "voiceMessage",
                "constructionNoise"
            ]
        },
        {
            "touchTime": 24.7973633,
            "touchPlayerPosition": -292.157043,
            "singleOrDouble": "4",
            "playingObjects": [
                "voiceMessage",
                "voiceAssistant",
                "constructionNoise"
            ]
        },
        {
            "touchTime": 26.03125,
            "touchPlayerPosition": -295.241821,
            "singleOrDouble": "2",
            "playingObjects": [
                "whiteCaneStone",
                "voiceAssistant",
                "constructionNoise"
            ]
        },
        {
            "touchTime": 27.4985352,
            "touchPlayerPosition": -298.909943,
            "singleOrDouble": "1",
            "playingObjects": [
                "whiteCaneStone",
                "constructionNoise"
            ]
        },
        {
            "touchTime": 32.90088,
            "touchPlayerPosition": -312.415741,
            "singleOrDouble": "1",
            "playingObjects": [
                "whiteCaneStone"
            ]
        },
        {
            "touchTime": 34.93506,
            "touchPlayerPosition": -317.500977,
            "singleOrDouble": "3",
            "playingObjects": [
                "voiceMessage",
                "constructionNoise"
            ]
        },
        {
            "touchTime": 35.43506,
            "touchPlayerPosition": -318.75174,
            "singleOrDouble": "4",
            "playingObjects": [
                "voiceMessage",
                "constructionNoise"
            ]
        },
        {
            "touchTime": 37.00244,
            "touchPlayerPosition": -322.67,
            "singleOrDouble": "2",
            "playingObjects": [
                "voiceAssistant",
                "constructionNoise"
            ]
        },
        {
            "touchTime": 40.6709,
            "touchPlayerPosition": -331.84082,
            "singleOrDouble": "2",
            "playingObjects": [
                "voiceAssistant"
            ]
        },
        {
            "touchTime": 44.3388672,
            "touchPlayerPosition": -341.011383,
            "singleOrDouble": "3",
            "playingObjects": [
                "constructionNoise"
            ]
        },
        {
            "touchTime": 47.26953,
            "touchPlayerPosition": -348.337616,
            "singleOrDouble": "1",
            "playingObjects": [
                "whiteCaneStone",
                "constructionNoise"
            ]
        },
        {
            "touchTime": 49.003418,
            "touchPlayerPosition": -352.673,
            "singleOrDouble": "4",
            "playingObjects": [
                "voiceMessage"
            ]
        },
        {
            "touchTime": 54.13916,
            "touchPlayerPosition": -365.5121,
            "singleOrDouble": "1",
            "playingObjects": [
                "whiteCaneStone",
                "voiceAssistant"
            ]
        },
        {
            "touchTime": 55.30664,
            "touchPlayerPosition": -368.430145,
            "singleOrDouble": "2",
            "playingObjects": [
                "whiteCaneStone",
                "voiceAssistant"
            ]
        },
        {
            "touchTime": 57.8828125,
            "touchPlayerPosition": -374.870453,
            "singleOrDouble": "3",
            "playingObjects": [
                "constructionNoise"
            ]
        },
        {
            "touchTime": 61.00049,
            "touchPlayerPosition": -382.665161,
            "singleOrDouble": "4",
            "playingObjects": [
                "voiceMessage",
                "constructionNoise"
            ]
        }
    ]
}